aaindexer/__init__.py
aaindexer/cli.py
aaindexer/models.py
aaindexer/parser.py
aaindexer/scrape.py
aaindexer-0.1.0.dist-info/entry_points.txt
aaindexer-0.1.0.dist-info/WHEEL
aaindexer-0.1.0.dist-info/METADATA
aaindexer-0.1.0.dist-info/RECORD
