Metadata-Version: 2.1
Name: aaindexer
Version: 0.1.0
Summary: 
Author: Michael Milton
Author-email: michael.r.milton@gmail.com
Requires-Python: >=3.8,<4.0
Classifier: Programming Language :: Python :: 3
Classifier: Programming Language :: Python :: 3.8
Classifier: Programming Language :: Python :: 3.9
Requires-Dist: click (>=7.0.0,<8.0.0)
Requires-Dist: pydantic (>=1.9.0,<2.0.0)
Requires-Dist: pyparsing (>=3.0.8,<4.0.0)
Requires-Dist: requests (>=2.27.1,<3.0.0)
Requires-Dist: rich (>=12.4.1,<13.0.0)
